[
    {
        "id": "richmond-harrison",
        "full-name": "Richmond Harrison",
        "size": "small",
        "team": "Seattle Garages",
        "former-teams": [],
        "sprites": [
            "01RichmondHarrison.png",
            "01RichmondHarrisonALT.png"
        ]
    },
    {
        "id": "mike-townsend",
        "full-name": "Mike Townsend",
        "size": "small",
        "team": "Hades Tigers",
        "former-teams": [
            "Canada Moist Talkers"
        ],
        "sprites": [
            "02MikeTownsend.png"
        ]
    },
    {
        "id": "wyatt-quitter",
        "full-name": "Wyatt Quitter",
        "size": "small",
        "team": "Tokyo Lift",
        "former-teams": [
            "Unlimited Tacos",
            "THE SHELLED ONE'S PODS"
        ],
        "sprites": [
            "03WyattQuitter.png",
            "03WyattQuitterALT.png",
            "03WyattQuitterALT2.png"
        ]
    },
    {
        "id": "conner-haley",
        "full-name": "Conner Haley",
        "size": "small",
        "team": "Dallas Steaks",
        "former-teams": [],
        "sprites": [
            "04ConnerHaley.png"
        ]
    },
    {
        "id": "cory-twelve",
        "full-name": "Cory Twelve",
        "size": "small",
        "team": "Yellowstone Magic",
        "former-teams": [],
        "sprites": [
            "05CoryTwelve.png"
        ]
    },
    {
        "id": "stephanie-winters",
        "full-name": "Stephanie Winters",
        "size": "small",
        "team": "Mexico City Wild Wings",
        "former-teams": [],
        "sprites": [
            "06StephanieWinters.png"
        ]
    },
    {
        "id": "landry-violence",
        "full-name": "Landry Violence",
        "size": "small",
        "team": "Hall Stars",
        "former-teams": [
            "Hades Tigers"
        ],
        "sprites": [
            "07LandryViolence.png",
            "07LandryViolenceALT.png"
        ]
    },
    {
        "id": "caligula-lotus",
        "full-name": "Caligula Lotus",
        "size": "large",
        "team": "Hall Stars",
        "former-teams": [
            "Boston Flowers"
        ],
        "sprites": [
            "08CaligulaLotus.png",
            "08CaligulaLotusALT.png"
        ]
    },
    {
        "id": "kiki-familia",
        "full-name": "Kiki Familia",
        "size": "small",
        "team": "Hall Stars",
        "former-teams": [
            "Canada Moist Talkers"
        ],
        "sprites": [
            "09KikiFamilia.png",
            "09KikiFamiliaALT.png"
        ]
    },
    {
        "id": "nagomi-nava",
        "full-name": "Nagomi Nava",
        "size": "small",
        "team": "Hellmouth Sunbeams",
        "former-teams": [],
        "sprites": [
            "10NagomiNava.png"
        ]
    },
    {
        "id": "forrest-best",
        "full-name": "Forrest Best",
        "size": "small",
        "team": "Baltimore Crabs",
        "former-teams": [],
        "sprites": [
            "11ForrestBest.png"
        ]
    },
    {
        "id": "jessica-telephone",
        "full-name": "Jessica Telephone",
        "size": "small",
        "team": "Kansas City Breath Mints",
        "former-teams": [
            "Dallas Steaks",
            "Philly Pies",
            "Hades Tigers",
            "THE SHELLED ONE'S PODS"
        ],
        "sprites": [
            "12JessicaTelephone.png",
            "12JessicaTelephoneALT.png",
            "12JessicaTelephoneALT2.png",
            "12JessicaTelephoneALT3.png",
            "12JessicaTelephoneALT4.png"
        ]
    },
    {
        "id": "don-mitchell",
        "full-name": "Don Mitchell",
        "size": "small",
        "team": "San Francisco Lovers",
        "former-teams": [],
        "sprites": [
            "13DonMitchell.png"
        ]
    },
    {
        "id": "baby-triumphant",
        "full-name": "Baby Triumphant",
        "size": "small",
        "team": "Chicago Firefighters",
        "former-teams": [],
        "sprites": [
            "14BabyTriumphant.png"
        ]
    },
    {
        "id": "alexandria-rosales",
        "full-name": "Alexandria Rosales",
        "size": "small",
        "team": "Houston Spies",
        "former-teams": [],
        "sprites": [
            "15AlexandriaRosales.png"
        ]
    },
    {
        "id": "lowe-forbes",
        "full-name": "Lowe Forbes",
        "size": "small",
        "team": "Breckenridge Jazz Hands",
        "former-teams": [],
        "sprites": [
            "16LoweForbes.png"
        ]
    },
    {
        "id": "sixpack-dogwalker",
        "full-name": "Sixpack Dogwalker",
        "size": "large",
        "team": "Dallas Steaks",
        "former-teams": [
            "Hawai'i Fridays"
        ],
        "sprites": [
            "17SixpackDogwalker.png",
            "17SixpackDogwalkerALT.png"
        ]
    },
    {
        "id": "dominic-marijuana",
        "full-name": "Dominic Marijuana",
        "size": "small",
        "team": "Hall Stars",
        "former-teams": [
            "New York Millennials"
        ],
        "sprites": [
            "18DominicMarijuana.png",
            "18DominicMarijuanaALT.png"
        ]
    },
    {
        "id": "randall-marijuana",
        "full-name": "Randall Marijuana",
        "size": "small",
        "team": "Hall Stars",
        "former-teams": [
            "Hellmouth Sunbeams",
            "Breckenridge Jazz Hands"
        ],
        "sprites": [
            "19RandallMarijuana.png",
            "19RandallMarijuanaALT.png",
            "19RandallMarijuanaALT2.png"
        ]
    },
    {
        "id": "don-elliott",
        "full-name": "Don Elliott",
        "size": "small",
        "team": "Miami Dale",
        "former-teams": [],
        "sprites": [
            "20DonElliott.png"
        ]
    },
    {
        "id": "boyfriend-monreal",
        "full-name": "Boyfriend Monreal",
        "size": "small",
        "team": "Hall Stars",
        "former-teams": [
            "Kansas City Breath Mints"
        ],
        "sprites": [
            "21BoyfriendMonreal.png",
            "21BoyfriendMonrealALT.png"
        ]
    },
    {
        "id": "gunther-o-brian",
        "full-name": "Gunther O Brian",
        "size": "small",
        "team": "Charleston Shoe Thieves",
        "former-teams": [],
        "sprites": [
            "22GuntherOBrian.png"
        ]
    },
    {
        "id": "fish-summer",
        "full-name": "Fish Summer",
        "size": "large",
        "team": "Canada Moist Talkers",
        "former-teams": [
            "Hades Tigers"
        ],
        "sprites": [
            "23FishSummer.png",
            "23FishSummerALT.png"
        ]
    },
    {
        "id": "zion-aliciakeyes",
        "full-name": "Zion Aliciakeyes",
        "size": "large",
        "team": "Hades Tigers",
        "former-teams": [],
        "sprites": [
            "24ZionAliciakeyes.png"
        ]
    },
    {
        "id": "jaylen-hotdogfingers",
        "full-name": "Jaylen Hotdogfingers",
        "size": "small",
        "team": "San Francisco Lovers",
        "former-teams": [
            "Seattle Garages",
            "Charleston Shoe Thieves",
            "THE SHELLED ONE'S PODS",
            "Hall Stars"
        ],
        "sprites": [
            "25JaylenHotdogfingers.png",
            "25JaylenHotdogfingersALT.png",
            "25JaylenHotdogfingersALT2.png",
            "25JaylenHotdogfingersALT3.png",
            "25JaylenHotdogfingersALT4.png",
            "25JaylenHotdogfingersALT5.png",
            "25JaylenHotdogfingersALT6.png"
        ]
    },
    {
        "id": "parker-meng",
        "full-name": "Parker Meng",
        "size": "small",
        "team": "San Francisco Lovers",
        "former-teams": [],
        "sprites": [
            "26ParkerMeng.png"
        ]
    },
    {
        "id": "york-silk",
        "full-name": "York Silk",
        "size": "small",
        "team": "Canada Moist Talkers",
        "former-teams": [
            "Hawai'i Fridays",
            "THE SHELLED ONE'S PODS"
        ],
        "sprites": [
            "27YorkSilk.png",
            "27YorkSilkALT.png",
            "27YorkSilkALT2.png"
        ]
    },
    {
        "id": "nan",
        "full-name": "NaN",
        "size": "small",
        "team": "San Francisco Lovers",
        "former-teams": [
            "Unlimited Tacos",
            "Houston Spies",
            "Mexico City Wild Wings"
        ],
        "sprites": [
            "28NaN.png",
            "28NaNALT.png",
            "28NaNALT2.png",
            "28NaNALT3.png"
        ]
    },
    {
        "id": "rivers-rosa",
        "full-name": "Rivers Rosa",
        "size": "small",
        "team": "Chicago Firefighters",
        "former-teams": [],
        "sprites": [
            "29RiversRosa.png"
        ]
    },
    {
        "id": "math-velazquez",
        "full-name": "Math Velazquez",
        "size": "large",
        "team": "Houston Spies",
        "former-teams": [],
        "sprites": [
            "30MathVelazquez.png"
        ]
    },
    {
        "id": "nagomi-mcdaniel",
        "full-name": "Nagomi McDaniel",
        "size": "small",
        "team": "Hawai'i Fridays",
        "former-teams": [
            "Baltimore Crabs",
            "Breckenridge Jazz Hands"
        ],
        "sprites": [
            "31NagomiMcDaniel.png",
            "31NagomiMcDanielALT.png",
            "31NagomiMcDanielALT2.png",
            "31NagomiMcDanielALT3.png"
        ]
    },
    {
        "id": "kline-greenlemon",
        "full-name": "Kline Greenlemon",
        "size": "small",
        "team": "Dallas Steaks",
        "former-teams": [],
        "sprites": [
            "32KlineGreenlemon.png"
        ]
    },
    {
        "id": "nolanestophia-patterson",
        "full-name": "Nolanestophia Patterson",
        "size": "small",
        "team": "Seattle Garages",
        "former-teams": [
            "Philly Pies",
            "Hades Tigers"
        ],
        "sprites": [
            "33NolanestophiaPatterson.png",
            "33NolanestophiaPattersonALT.png",
            "33NolanestophiaPattersonALT2.png",
            "33NolanestophiaPattersonALT3.png"
        ]
    },
    {
        "id": "ziwa-mueller",
        "full-name": "Ziwa Mueller",
        "size": "small",
        "team": "Canada Moist Talkers",
        "former-teams": [],
        "sprites": [
            "34ZiwaMueller.png"
        ]
    },
    {
        "id": "lars-taylor",
        "full-name": "Lars Taylor",
        "size": "small",
        "team": "Hellmouth Sunbeams",
        "former-teams": [],
        "sprites": [
            "35LarsTaylor.png"
        ]
    },
    {
        "id": "annie-roland",
        "full-name": "Annie Roland",
        "size": "small",
        "team": "RIV",
        "former-teams": [
            "Yellowstone Magic"
        ],
        "sprites": [
            "36AnnieRoland.png"
        ]
    },
    {
        "id": "margarito-nava",
        "full-name": "Margarito Nava",
        "size": "small",
        "team": "Boston Flowers",
        "former-teams": [],
        "sprites": [
            "37MargaritoNava.png"
        ]
    },
    {
        "id": "sebastian-telephone",
        "full-name": "Sebastian Telephone",
        "size": "small",
        "team": "RIV",
        "former-teams": [
            "Dallas Steaks",
            "Hall Stars"
        ],
        "sprites": [
            "38SebastianTelephone.png",
            "38SebastianTelephoneALT.png"
        ]
    },
    {
        "id": "axel-cardenas",
        "full-name": "Axel Cardenas",
        "size": "small",
        "team": "Mexico City Wild Wings",
        "former-teams": [],
        "sprites": [
            "39AxelCardenas.png"
        ]
    },
    {
        "id": "miguel-wheeler",
        "full-name": "Miguel Wheeler",
        "size": "small",
        "team": "RIV",
        "former-teams": [
            "Mexico City Wild Wings"
        ],
        "sprites": [
            "40MiguelWheeler.png"
        ]
    },
    {
        "id": "silvia-rugrat",
        "full-name": "Silvia Rugrat",
        "size": "small",
        "team": "Mexico City Wild Wings",
        "former-teams": [],
        "sprites": [
            "41SilviaRugrat.png"
        ]
    },
    {
        "id": "sosa-hayes",
        "full-name": "Sosa Hayes",
        "size": "small",
        "team": "Houston Spies",
        "former-teams": [
            "Mexico City Wild Wings"
        ],
        "sprites": [
            "42SosaHayes.png",
            "42SosaHayesALT.png"
        ]
    },
    {
        "id": "hahn-fox",
        "full-name": "Hahn Fox",
        "size": "small",
        "team": "Hellmouth Sunbeams",
        "former-teams": [
            "Miami Dale"
        ],
        "sprites": [
            "43HahnFox.png",
            "43HahnFoxALT.png",
            "43HahnFoxALT2.png"
        ]
    },
    {
        "id": "qais-dogwalker",
        "full-name": "Qais Dogwalker",
        "size": "small",
        "team": "Miami Dale",
        "former-teams": [],
        "sprites": [
            "44QaisDogwalker.png"
        ]
    },
    {
        "id": "rodriguez-internet",
        "full-name": "Rodriguez Internet",
        "size": "small",
        "team": "Kansas City Breath Mints",
        "former-teams": [],
        "sprites": [
            "45RodriguezInternet.png"
        ]
    },
    {
        "id": "cornelius-games",
        "full-name": "Cornelius Games",
        "size": "small",
        "team": "Charleston Shoe Thieves",
        "former-teams": [],
        "sprites": [
            "46CorneliusGames.png"
        ]
    },
    {
        "id": "thomas-dracaena",
        "full-name": "Thomas Dracaena",
        "size": "small",
        "team": "New York Millennials",
        "former-teams": [],
        "sprites": [
            "47ThomasDracaena.png"
        ]
    },
    {
        "id": "pitching-machine",
        "full-name": "Pitching Machine",
        "size": "small",
        "team": "Seattle Garages",
        "former-teams": [
            "Unlimited Tacos",
            "THE SHELLED ONE'S PODS"
        ],
        "sprites": [
            "48PitchingMachine.png",
            "48PitchingMachineALT.png",
            "48PitchingMachineALT2.png"
        ]
    },
    {
        "id": "isaac-rubberman",
        "full-name": "Isaac Rubberman",
        "size": "large",
        "team": "RIV",
        "former-teams": [
            "Boston Flowers"
        ],
        "sprites": [
            "49IsaacRubberman.png"
        ]
    },
    {
        "id": "nicholas-mora",
        "full-name": "Nicholas Mora",
        "size": "small",
        "team": "Philly Pies",
        "former-teams": [],
        "sprites": [
            "50NicholasMora.png",
            "50NicholasMoraALT.png"
        ]
    },
    {
        "id": "goobie-ballson",
        "full-name": "Goobie Ballson",
        "size": "large",
        "team": "Chicago Firefighters",
        "former-teams": [],
        "sprites": [
            "51GoobieBallson.png",
            "51GoobieBallson1.png"
        ]
    },
    {
        "id": "joe-voorhees",
        "full-name": "Joe Voorhees",
        "size": "small",
        "team": "Hellmouth Sunbeams",
        "former-teams": [
            "Canada Moist Talkers",
            "Charleston Shoe Thieves"
        ],
        "sprites": [
            "52JoeVoorhees.png",
            "52JoeVoorheesALT.png",
            "52JoeVoorheesALT2.png",
            "52JoeVoorheesALT3.png"
        ]
    },
    {
        "id": "knight-triumphant",
        "full-name": "Knight Triumphant",
        "size": "small",
        "team": "San Francisco Lovers",
        "former-teams": [],
        "sprites": [
            "53KnightTriumphant.png"
        ]
    },
    {
        "id": "allison-abbott",
        "full-name": "Allison Abbott",
        "size": "small",
        "team": "Dallas Steaks",
        "former-teams": [
            "Seattle Garages"
        ],
        "sprites": [
            "54AllisonAbbott.png",
            "54AllisonAbbottALT.png"
        ]
    },
    {
        "id": "axel-trololol",
        "full-name": "Axel Trololol",
        "size": "large",
        "team": "Hall Stars",
        "former-teams": [
            "Kansas City Breath Mints",
            "Chicago Firefighters",
            "Baltimore Crabs",
            "THE SHELLED ONE'S PODS"
        ],
        "sprites": [
            "55AxelTrololol.png",
            "55AxelTrolololALT.png",
            "55AxelTrolololALT2.png",
            "55AxelTrolololALT3.png",
            "55AxelTrolololALT4.png"
        ]
    },
    {
        "id": "inky-rutledge",
        "full-name": "Inky Rutledge",
        "size": "small",
        "team": "Yellowstone Magic",
        "former-teams": [],
        "sprites": [
            "56InkyRutledge.png"
        ]
    },
    {
        "id": "sandie-turner",
        "full-name": "Sandie Turner",
        "size": "small",
        "team": "New York Millennials",
        "former-teams": [],
        "sprites": [
            "57SandieTurner.png"
        ]
    },
    {
        "id": "tamara-crankit",
        "full-name": "Tamara Crankit",
        "size": "small",
        "team": "Breckenridge Jazz Hands",
        "former-teams": [],
        "sprites": [
            "58TamaraCrankit.png"
        ]
    },
    {
        "id": "kichiro-guerra",
        "full-name": "Kichiro Guerra",
        "size": "small",
        "team": "San Francisco Lovers",
        "former-teams": [],
        "sprites": [
            "59KichiroGuerra.png"
        ]
    },
    {
        "id": "patty-fox",
        "full-name": "Patty Fox",
        "size": "small",
        "team": "New York Millennials",
        "former-teams": [],
        "sprites": [
            "60PattyFox.png"
        ]
    },
    {
        "id": "wyatt-pothos",
        "full-name": "Wyatt Pothos",
        "size": "small",
        "team": "Breckenridge Jazz Hands",
        "former-teams": [
            "Unlimited Tacos",
            "THE SHELLED ONE'S PODS"
        ],
        "sprites": [
            "61WyattPothos.png",
            "61WyattPothosALT.png",
            "61WyattPothosALT2.png"
        ]
    },
    {
        "id": "cannonball-sports",
        "full-name": "Cannonball Sports",
        "size": "small",
        "team": "Miami Dale",
        "former-teams": [],
        "sprites": [
            "62CannonballSports.png"
        ]
    },
    {
        "id": "elvis-figueroa",
        "full-name": "Elvis Figueroa",
        "size": "small",
        "team": "Philly Pies",
        "former-teams": [],
        "sprites": [
            "63ElvisFigueroa.png"
        ]
    },
    {
        "id": "fitzgerald-blackburn",
        "full-name": "Fitzgerald Blackburn",
        "size": "small",
        "team": "Houston Spies",
        "former-teams": [],
        "sprites": [
            "64FitzgeraldBlackburn.png"
        ]
    },
    {
        "id": "tot-fox",
        "full-name": "Tot Fox",
        "size": "small",
        "team": "Baltimore Crabs",
        "former-teams": [
            "Breckenridge Jazz Hands"
        ],
        "sprites": [
            "65TotFox.png",
            "65TotFoxALT.png"
        ]
    },
    {
        "id": "tillman-henderson",
        "full-name": "Tillman Henderson",
        "size": "small",
        "team": "Charleston Shoe Thieves",
        "former-teams": [
            "Baltimore Crabs"
        ],
        "sprites": [
            "66TillmanHenderson.png",
            "66TillmanHendersonALT.png"
        ]
    },
    {
        "id": "oliver-notarobot",
        "full-name": "Oliver Notarobot",
        "size": "large",
        "team": "Seattle Garages",
        "former-teams": [
            "Canada Moist Talkers",
            "Baltimore Crabs"
        ],
        "sprites": [
            "67OliverNotarobot.png",
            "67OliverNotarobotALT.png",
            "67OliverNotarobotALT2.png"
        ]
    },
    {
        "id": "adalberto-tosser",
        "full-name": "Adalberto Tosser",
        "size": "small",
        "team": "Baltimore Crabs",
        "former-teams": [],
        "sprites": [
            "68AdalbertoTosser.png"
        ]
    },
    {
        "id": "blood-hamburger",
        "full-name": "Blood Hamburger",
        "size": "small",
        "team": "Charleston Shoe Thieves",
        "former-teams": [],
        "sprites": [
            "69BloodHamburger.png"
        ]
    },
    {
        "id": "leach-ingram",
        "full-name": "Leach Ingram",
        "size": "small",
        "team": "Kansas City Breath Mints",
        "former-teams": [],
        "sprites": [
            "70LeachIngram.png"
        ]
    },
    {
        "id": "francisco-preston",
        "full-name": "Francisco Preston",
        "size": "small",
        "team": "Yellowstone Magic",
        "former-teams": [],
        "sprites": [
            "71FranciscoPreston.png"
        ]
    },
    {
        "id": "spears-taylor",
        "full-name": "Spears Taylor",
        "size": "large",
        "team": "Hawai'i Fridays",
        "former-teams": [
            "Philly Pies",
            "Hades Tigers"
        ],
        "sprites": [
            "72SpearsTaylor.png",
            "72SpearsTaylorALT.png",
            "72SpearsTaylorALT2.png"
        ]
    },
    {
        "id": "beck-whitney",
        "full-name": "Beck Whitney",
        "size": "small",
        "team": "Miami Dale",
        "former-teams": [
            "Boston Flowers"
        ],
        "sprites": [
            "73BeckWhitney.png",
            "73BeckWhitneyALT.png"
        ]
    },
    {
        "id": "lou-roseheart",
        "full-name": "Lou Roseheart",
        "size": "small",
        "team": "Chicago Firefighters",
        "former-teams": [],
        "sprites": [
            "74LouRoseheart.png"
        ]
    },
    {
        "id": "sigmund-castillo",
        "full-name": "Sigmund Castillo",
        "size": "large",
        "team": "Hellmouth Sunbeams",
        "former-teams": [
            "San Francisco Lovers"
        ],
        "sprites": [
            "75SigmundCastillo.png",
            "75SigmundCastilloALT.png"
        ]
    },
    {
        "id": "chorby-soul",
        "full-name": "Chorby Soul",
        "size": "small",
        "team": "RIV",
        "former-teams": [
            "New York Millennials"
        ],
        "sprites": [
            "76ChorbySoul.png"
        ]
    },
    {
        "id": "carmelo-plums",
        "full-name": "Carmelo Plums",
        "size": "small",
        "team": "Pending Team",
        "former-teams": [],
        "sprites": [
            "77CarmeloPlums.png"
        ]
    },
    {
        "id": "sexton-wheerer",
        "full-name": "Sexton Wheerer",
        "size": "large",
        "team": "Unlimited Tacos",
        "former-teams": [],
        "sprites": [
            "78SextonWheerer.png"
        ]
    },
    {
        "id": "son-scotch",
        "full-name": "Son Scotch",
        "size": "small",
        "team": "Houston Spies",
        "former-teams": [],
        "sprites": [
            "79SonScotch.png"
        ]
    },
    {
        "id": "atlas-jonbois",
        "full-name": "Atlas Jonbois",
        "size": "small",
        "team": "RIV",
        "former-teams": [
            "Charleston Shoe Thieves"
        ],
        "sprites": [
            "80AtlasJonbois.png"
        ]
    },
    {
        "id": "washer-barajas",
        "full-name": "Washer Barajas",
        "size": "large",
        "team": "Yellowstone Magic",
        "former-teams": [],
        "sprites": [
            "81WasherBarajas.png"
        ]
    },
    {
        "id": "winnie-hess",
        "full-name": "Winnie Hess",
        "size": "small",
        "team": "Kansas City Breath Mints",
        "former-teams": [],
        "sprites": [
            "82WinnieHess.png",
            "82WinnieHessALT.png"
        ]
    },
    {
        "id": "cell-barajas",
        "full-name": "Cell Barajas",
        "size": "small",
        "team": "Mexico City Wild Wings",
        "former-teams": [],
        "sprites": [
            "83CellBarajas.png"
        ]
    },
    {
        "id": "august-sky",
        "full-name": "August Sky",
        "size": "small",
        "team": "Dallas Steaks",
        "former-teams": [
            "Breckenridge Jazz Hands"
        ],
        "sprites": [
            "84AugustSky.png",
            "84AugustSkyALT.png"
        ]
    },
    {
        "id": "malik-destiny",
        "full-name": "Malik Destiny",
        "size": "small",
        "team": "Seattle Garages",
        "former-teams": [],
        "sprites": [
            "85MalikDestiny.png"
        ]
    },
    {
        "id": "farrell-seagull",
        "full-name": "Farrell Seagull",
        "size": "small",
        "team": "Philly Pies",
        "former-teams": [
            "Miami Dale",
            "Seattle Garages"
        ],
        "sprites": [
            "86FarrellSeagull.png",
            "86FarrellSeagullALT.png",
            "86FarrellSeagullALT2.png"
        ]
    },
    {
        "id": "fletcher-yamamoto",
        "full-name": "Fletcher Yamamoto",
        "size": "small",
        "team": "Hawai'i Fridays",
        "former-teams": [],
        "sprites": [
            "87FletcherYamamoto.png"
        ]
    },
    {
        "id": "alaynabella-hollywood",
        "full-name": "Alaynabella Hollywood",
        "size": "small",
        "team": "Boston Flowers",
        "former-teams": [
            "Hellmouth Sunbeams"
        ],
        "sprites": [
            "88AlaynabellaHollywood.png",
            "88AlaynabellaHollywoodALT.png"
        ]
    },
    {
        "id": "joshua-butt",
        "full-name": "Joshua Butt",
        "size": "small",
        "team": "Chicago Firefighters",
        "former-teams": [],
        "sprites": [
            "89JoshuaButt.png"
        ]
    },
    {
        "id": "penelope-mathews",
        "full-name": "Penelope Mathews",
        "size": "small",
        "team": "New York Millennials",
        "former-teams": [],
        "sprites": [
            "90PenelopeMathews.png",
            "90PenelopeMathewsALT.png"
        ]
    },
    {
        "id": "ortiz-lopez",
        "full-name": "Ortiz Lopez",
        "size": "small",
        "team": "San Francisco Lovers",
        "former-teams": [],
        "sprites": [
            "91OrtizLopez.png"
        ]
    },
    {
        "id": "halexandrey-walton",
        "full-name": "Halexandrey Walton",
        "size": "small",
        "team": "Unlimited Tacos",
        "former-teams": [
            "Yellowstone Magic"
        ],
        "sprites": [
            "92HalexandreyWalton.png",
            "92HalexandreyWaltonALT.png"
        ]
    },
    {
        "id": "miki-santana",
        "full-name": "Miki Santana",
        "size": "small",
        "team": "RIV",
        "former-teams": [
            "Houston Spies"
        ],
        "sprites": [
            "93MikiSantana.png"
        ]
    },
    {
        "id": "stu-trololol",
        "full-name": "Stu Trololol",
        "size": "small",
        "team": "Charleston Shoe Thieves",
        "former-teams": [],
        "sprites": [
            "94StuTrololol.png"
        ]
    },
    {
        "id": "marquez-clark",
        "full-name": "Marquez Clark",
        "size": "small",
        "team": "Kansas City Breath Mints",
        "former-teams": [],
        "sprites": [
            "95MarquezClark.png"
        ]
    },
    {
        "id": "agan-harrison",
        "full-name": "Agan Harrison",
        "size": "small",
        "team": "Breckenridge Jazz Hands",
        "former-teams": [],
        "sprites": [
            "96AganHarrison.png"
        ]
    },
    {
        "id": "tyler-violet",
        "full-name": "Tyler Violet",
        "size": "small",
        "team": "RIV",
        "former-teams": [
            "Canada Moist Talkers"
        ],
        "sprites": [
            "97TylerViolet.png"
        ]
    },
    {
        "id": "joshua-watson",
        "full-name": "Joshua Watson",
        "size": "small",
        "team": "Mexico City Wild Wings",
        "former-teams": [
            "Baltimore Crabs",
            "Chicago Firefighters"
        ],
        "sprites": [
            "98JoshuaWatson.png",
            "98JoshuaWatsonALT.png",
            "98JoshuaWatsonALT2.png"
        ]
    },
    {
        "id": "leach-herman",
        "full-name": "Leach Herman",
        "size": "small",
        "team": "Dallas Steaks",
        "former-teams": [],
        "sprites": [
            "99LeachHerman.png"
        ]
    },
    {
        "id": "yazmin-mason",
        "full-name": "Yazmin Mason",
        "size": "small",
        "team": "Hall Stars",
        "former-teams": [
            "Hades Tigers"
        ],
        "sprites": [
            "100YazminMason.png",
            "100YazminMasonALT.png",
            "100YazminMasonALT2.png"
        ]
    },
    {
        "id": "juice-collins",
        "full-name": "Juice Collins",
        "size": "small",
        "team": "Hawai'i Fridays",
        "former-teams": [],
        "sprites": [
            "101JuiceCollins.png"
        ]
    },
    {
        "id": "jasmine-washington",
        "full-name": "Jasmine Washington",
        "size": "small",
        "team": "Miami Dale",
        "former-teams": [],
        "sprites": [
            "102JasmineWashington.png"
        ]
    },
    {
        "id": "inez-owens",
        "full-name": "Inez Owens",
        "size": "small",
        "team": "Boston Flowers",
        "former-teams": [],
        "sprites": [
            "103InezOwens.png"
        ]
    },
    {
        "id": "alexander-horne",
        "full-name": "Alexander Horne",
        "size": "small",
        "team": "San Francisco Lovers",
        "former-teams": [
            "Hellmouth Sunbeams"
        ],
        "sprites": [
            "104AlexanderHorne.png",
            "104AlexanderHorneALT.png"
        ]
    },
    {
        "id": "pudge-nakatamo",
        "full-name": "Pudge Nakatamo",
        "size": "small",
        "team": "Pending Team",
        "former-teams": [],
        "sprites": [
            "105PudgeNakatamo.png"
        ]
    },
    {
        "id": "elijah-valenzuela",
        "full-name": "Elijah Valenzuela",
        "size": "small",
        "team": "Breckenridge Jazz Hands",
        "former-teams": [
            "Hawai'i Fridays"
        ],
        "sprites": [
            "106ElijahValenzuela.png",
            "106ElijahValenzuelaALT.png"
        ]
    },
    {
        "id": "alejandro-leaf",
        "full-name": "Alejandro Leaf",
        "size": "small",
        "team": "New York Millennials",
        "former-teams": [
            "Unlimited Tacos"
        ],
        "sprites": [
            "107AlejandroLeaf.png",
            "107AlejandroLeafALT.png",
            "107AlejandroLeafALT2.png"
        ]
    },
    {
        "id": "luis-acevedo",
        "full-name": "Luis Acevedo",
        "size": "small",
        "team": "Baltimore Crabs",
        "former-teams": [
            "Seattle Garages"
        ],
        "sprites": [
            "108LuisAcevedo.png",
            "108LuisAcevedoALT.png"
        ]
    },
    {
        "id": "fynn-doyle",
        "full-name": "Fynn Doyle",
        "size": "small",
        "team": "Pending Team",
        "former-teams": [],
        "sprites": [
            "109FynnDoyle.png"
        ]
    },
    {
        "id": "thomas-kirby",
        "full-name": "Thomas Kirby",
        "size": "small",
        "team": "RIV",
        "former-teams": [
            "Dallas Steaks",
            "Chicago Firefighters"
        ],
        "sprites": [
            "110ThomasKirby.png",
            "110ThomasKirbyALT.png"
        ]
    },
    {
        "id": "chorby-short",
        "full-name": "Chorby Short",
        "size": "small",
        "team": "Yellowstone Magic",
        "former-teams": [],
        "sprites": [
            "111ChorbyShort.png"
        ]
    },
    {
        "id": "logan-horseman",
        "full-name": "Logan Horseman",
        "size": "small",
        "team": "Miami Dale",
        "former-teams": [],
        "sprites": [
            "112LoganHorseman.png"
        ]
    },
    {
        "id": "peanutiel-duffy",
        "full-name": "Peanutiel Duffy",
        "size": "huge",
        "team": "Chicago Firefighters",
        "former-teams": [
            "Hades Tigers",
            "THE SHELLED ONE'S PODS"
        ],
        "sprites": [
            "113PeanutielDuffy.png",
            "113PeanutielDuffyALT.png",
            "113PeanutielDuffyALT2.png"
        ]
    },
    {
        "id": "peanut-holloway",
        "full-name": "Peanut Holloway",
        "size": "small",
        "team": "Chicago Firefighters",
        "former-teams": [
            "Philly Pies",
            "THE SHELLED ONE'S PODS"
        ],
        "sprites": [
            "114PeanutHolloway.png",
            "114PeanutHollowayALT.png",
            "114PeanutHollowayALT2.png"
        ]
    },
    {
        "id": "peanut-bong",
        "full-name": "Peanut Bong",
        "size": "small",
        "team": "Unlimited Tacos",
        "former-teams": [
            "Miami Dale",
            "THE SHELLED ONE'S PODS"
        ],
        "sprites": [
            "115PeanutBong.png",
            "115PeanutBongALT.png",
            "115PeanutBongALT2.png"
        ]
    },
    {
        "id": "hotbox-sato",
        "full-name": "Hotbox Sato",
        "size": "small",
        "team": "Pending Team",
        "former-teams": [],
        "sprites": [
            "116HotboxSato.png",
            "116HotboxSatoALT.png"
        ]
    },
    {
        "id": "howell-franklin",
        "full-name": "Howell Franklin",
        "size": "large",
        "team": "Pending Team",
        "former-teams": [],
        "sprites": [
            "117HowellFranklin.png",
            "117HowellFranklinALT.png"
        ]
    },
    {
        "id": "workman-gloom",
        "full-name": "Workman Gloom",
        "size": "small",
        "team": "Pending Team",
        "former-teams": [],
        "sprites": [
            "118WorkmanGloom.png",
            "118WorkmanGloomALT.png",
            "118WorkmanGloomALT2.png"
        ]
    },
    {
        "id": "beasley-gloom",
        "full-name": "Beasley Gloom",
        "size": "small",
        "team": "Pending Team",
        "former-teams": [],
        "sprites": [
            "119BeasleyGloom.png",
            "119BeasleyGloomALT.png"
        ]
    },
    {
        "id": "esme-ramsey",
        "full-name": "Esme Ramsey",
        "size": "small",
        "team": "Pending Team",
        "former-teams": [],
        "sprites": [
            "120EsmeRamsey.png"
        ]
    },
    {
        "id": "wyatt-dovenpart",
        "full-name": "Wyatt Dovenpart",
        "size": "small",
        "team": "Pending Team",
        "former-teams": [],
        "sprites": [
            "121WyattDovenpart.png"
        ]
    },
    {
        "id": "basilio-fig",
        "full-name": "Basilio Fig",
        "size": "small",
        "team": "Pending Team",
        "former-teams": [],
        "sprites": [
            "122BasilioFig.png",
            "122BasilioFigALT.png"
        ]
    },
    {
        "id": "quack-enjoyable",
        "full-name": "Quack Enjoyable",
        "size": "small",
        "team": "Pending Team",
        "former-teams": [],
        "sprites": [
            "123QuackEnjoyable.png",
            "123QuackEnjoyableALT.png"
        ]
    },
    {
        "id": "summers-pony",
        "full-name": "Summers Pony",
        "size": "small",
        "team": "Pending Team",
        "former-teams": [],
        "sprites": [
            "124SummersPony.png",
            "124SummersPonyALT.png",
            "124SummersPonyALT2.png"
        ]
    },
    {
        "id": "evelton-mcblase",
        "full-name": "Evelton McBlase",
        "size": "small",
        "team": "Pending Team",
        "former-teams": [],
        "sprites": [
            "125EveltonMcBlase.png"
        ]
    },
    {
        "id": "evelton-mcblase-i-i",
        "full-name": "Evelton McBlase I I",
        "size": "small",
        "team": "Pending Team",
        "former-teams": [],
        "sprites": [
            "126EveltonMcBlaseII.png",
            "126EveltonMcBlaseIIALT.png",
            "126EveltonMcBlaseIIALT2.png"
        ]
    },
    {
        "id": "lenny-spruce",
        "full-name": "Lenny Spruce",
        "size": "large",
        "team": "Pending Team",
        "former-teams": [],
        "sprites": [
            "127LennySpruce.png"
        ]
    },
    {
        "id": "hiroto-cerna",
        "full-name": "Hiroto Cerna",
        "size": "large",
        "team": "Pending Team",
        "former-teams": [],
        "sprites": [
            "128HirotoCerna.png"
        ]
    },
    {
        "id": "miguel-javier",
        "full-name": "Miguel Javier",
        "size": "large",
        "team": "Pending Team",
        "former-teams": [],
        "sprites": [
            "129MiguelJavier.png"
        ]
    },
    {
        "id": "paul-barnes",
        "full-name": "Paul Barnes",
        "size": "small",
        "team": "Pending Team",
        "former-teams": [],
        "sprites": [
            "130PaulBarnes.png"
        ]
    },
    {
        "id": "walton-sports",
        "full-name": "Walton Sports",
        "size": "small",
        "team": "Pending Team",
        "former-teams": [],
        "sprites": [
            "131WaltonSports.png"
        ]
    },
    {
        "id": "emmett-internet",
        "full-name": "Emmett Internet",
        "size": "small",
        "team": "Pending Team",
        "former-teams": [],
        "sprites": [
            "132EmmettInternet.png",
            "132EmmettInternetALT.png"
        ]
    },
    {
        "id": "valentine-games",
        "full-name": "Valentine Games",
        "size": "small",
        "team": "Pending Team",
        "former-teams": [],
        "sprites": [
            "133ValentineGames.png",
            "133ValentineGamesALT.png",
            "133ValentineGamesALT2.png",
            "133ValentineGamesALT3.png",
            "133ValentineGamesALT4.png"
        ]
    },
    {
        "id": "betsy-trombone",
        "full-name": "Betsy Trombone",
        "size": "small",
        "team": "Pending Team",
        "former-teams": [],
        "sprites": [
            "134BetsyTrombone.png",
            "134BetsyTromboneALT.png"
        ]
    },
    {
        "id": "nandy-fantastic",
        "full-name": "Nandy Fantastic",
        "size": "small",
        "team": "Pending Team",
        "former-teams": [],
        "sprites": [
            "135NandyFantastic.png"
        ]
    },
    {
        "id": "oscar-dollie",
        "full-name": "Oscar Dollie",
        "size": "large",
        "team": "Pending Team",
        "former-teams": [],
        "sprites": [
            "136OscarDollie.png"
        ]
    },
    {
        "id": "socks-maybe",
        "full-name": "Socks Maybe",
        "size": "small",
        "team": "Pending Team",
        "former-teams": [],
        "sprites": [
            "137SocksMaybe.png"
        ]
    },
    {
        "id": "kennedy-meh",
        "full-name": "Kennedy Meh",
        "size": "small",
        "team": "Pending Team",
        "former-teams": [],
        "sprites": [
            "138KennedyMeh.png",
            "138KennedyMehALT.png"
        ]
    },
    {
        "id": "forrest-bookbaby",
        "full-name": "Forrest Bookbaby",
        "size": "small",
        "team": "Pending Team",
        "former-teams": [],
        "sprites": [
            "139ForrestBookbaby.png",
            "139ForrestBookbabyALT.png"
        ]
    },
    {
        "id": "gray-alvarado",
        "full-name": "Gray Alvarado",
        "size": "small",
        "team": "Pending Team",
        "former-teams": [],
        "sprites": [
            "140GrayAlvarado.png"
        ]
    },
    {
        "id": "sutton-dreamy",
        "full-name": "Sutton Dreamy",
        "size": "small",
        "team": "Pending Team",
        "former-teams": [],
        "sprites": [
            "141SuttonDreamy.png",
            "141SuttonDreamyALT.png"
        ]
    },
    {
        "id": "kennedy-loser",
        "full-name": "Kennedy Loser",
        "size": "small",
        "team": "Pending Team",
        "former-teams": [],
        "sprites": [
            "142KennedyLoser.png"
        ]
    },
    {
        "id": "silvaire-roadhouse",
        "full-name": "Silvaire Roadhouse",
        "size": "small",
        "team": "Pending Team",
        "former-teams": [],
        "sprites": [
            "143SilvaireRoadhouse.png"
        ]
    },
    {
        "id": "combs-duende",
        "full-name": "Combs Duende",
        "size": "small",
        "team": "Pending Team",
        "former-teams": [],
        "sprites": [
            "144CombsDuende.png"
        ]
    },
    {
        "id": "moody-cookbook",
        "full-name": "Moody Cookbook",
        "size": "small",
        "team": "Pending Team",
        "former-teams": [],
        "sprites": [
            "145MoodyCookbook.png"
        ]
    },
    {
        "id": "nagomi-meng",
        "full-name": "Nagomi Meng",
        "size": "small",
        "team": "Pending Team",
        "former-teams": [],
        "sprites": [
            "146NagomiMeng.png"
        ]
    },
    {
        "id": "hiroto-wilcox",
        "full-name": "Hiroto Wilcox",
        "size": "small",
        "team": "Pending Team",
        "former-teams": [],
        "sprites": [
            "147HirotoWilcox.png"
        ]
    },
    {
        "id": "dunlap-figueroa",
        "full-name": "Dunlap Figueroa",
        "size": "small",
        "team": "Pending Team",
        "former-teams": [],
        "sprites": [
            "148DunlapFigueroa.png"
        ]
    },
    {
        "id": "tyreek-olive",
        "full-name": "Tyreek Olive",
        "size": "small",
        "team": "Pending Team",
        "former-teams": [],
        "sprites": [
            "149TyreekOlive.png",
            "149TyreekOliveALT.png"
        ]
    },
    {
        "id": "morrow-doyle",
        "full-name": "Morrow Doyle",
        "size": "large",
        "team": "Pending Team",
        "former-teams": [],
        "sprites": [
            "150MorrowDoyle.png",
            "150MorrowDoyleALT.png",
            "150MorrowDoyleALT2.png"
        ]
    },
    {
        "id": "sebastian-sunshine",
        "full-name": "Sebastian Sunshine",
        "size": "small",
        "team": "Pending Team",
        "former-teams": [],
        "sprites": [
            "151SebastianSunshine.png",
            "151SebastianSunshineALT.png"
        ]
    },
    {
        "id": "scrap-murphy",
        "full-name": "Scrap Murphy",
        "size": "small",
        "team": "Pending Team",
        "former-teams": [],
        "sprites": [
            "152ScrapMurphy.png",
            "152ScrapMurphyALT.png"
        ]
    },
    {
        "id": "aldon-cashmoney",
        "full-name": "Aldon Cashmoney",
        "size": "small",
        "team": "Pending Team",
        "former-teams": [],
        "sprites": [
            "153AldonCashmoney.png",
            "153AldonCashmoneyALT.png",
            "153AldonCashmoneyALT2.png"
        ]
    },
    {
        "id": "mcdowell-mason",
        "full-name": "McDowell Mason",
        "size": "small",
        "team": "Pending Team",
        "former-teams": [],
        "sprites": [
            "154McDowellMason.png"
        ]
    },
    {
        "id": "francisca-sasquatch",
        "full-name": "Francisca Sasquatch",
        "size": "small",
        "team": "Pending Team",
        "former-teams": [],
        "sprites": [
            "155FranciscaSasquatch.png",
            "155FranciscaSasquatchALT.png",
            "155FranciscaSasquatchALT2.png"
        ]
    },
    {
        "id": "patel-beyonce",
        "full-name": "Patel Beyonce",
        "size": "small",
        "team": "Pending Team",
        "former-teams": [],
        "sprites": [
            "156PatelBeyonce.png",
            "156PatelBeyonceALT.png",
            "156PatelBeyonceALT2.png"
        ]
    },
    {
        "id": "mummy-melcon",
        "full-name": "Mummy Melcon",
        "size": "small",
        "team": "Pending Team",
        "former-teams": [],
        "sprites": [
            "157MummyMelcon.png"
        ]
    },
    {
        "id": "paula-turnip",
        "full-name": "Paula Turnip",
        "size": "small",
        "team": "Pending Team",
        "former-teams": [],
        "sprites": [
            "158PaulaTurnip.png",
            "158PaulaTurnipALT.png"
        ]
    },
    {
        "id": "ren-morin",
        "full-name": "Ren Morin",
        "size": "large",
        "team": "Pending Team",
        "former-teams": [],
        "sprites": [
            "159RenMorin.png"
        ]
    },
    {
        "id": "usurper-violet",
        "full-name": "Usurper Violet",
        "size": "large",
        "team": "Pending Team",
        "former-teams": [],
        "sprites": [
            "160UsurperViolet.png"
        ]
    },
    {
        "id": "dudley-mueller",
        "full-name": "Dudley Mueller",
        "size": "small",
        "team": "Pending Team",
        "former-teams": [],
        "sprites": [
            "161DudleyMueller.png"
        ]
    },
    {
        "id": "sandoval-crossing",
        "full-name": "Sandoval Crossing",
        "size": "small",
        "team": "Pending Team",
        "former-teams": [],
        "sprites": [
            "162SandovalCrossing.png"
        ]
    },
    {
        "id": "sutton-bishop",
        "full-name": "Sutton Bishop",
        "size": "small",
        "team": "Pending Team",
        "former-teams": [],
        "sprites": [
            "163SuttonBishop.png"
        ]
    }
]